epsbasin/__init__.py
epsbasin/epsbasin.py
epsbasin-0.2.0.dist-info/LICENSE
epsbasin-0.2.0.dist-info/METADATA
epsbasin-0.2.0.dist-info/WHEEL
epsbasin-0.2.0.dist-info/RECORD
