Metadata-Version: 2.3
Name: epsbasin
Version: 0.2.0
Summary: Tools for computing and visualizing ε-attracting basin
License: MIT
Author: Yusuke Imoto
Author-email: imoto.yusuke.4e@kyoto-u.ac.jp
Requires-Python: >=3.10
Classifier: License :: OSI Approved :: MIT License
Classifier: Programming Language :: Python :: 3
Classifier: Programming Language :: Python :: 3.10
Classifier: Programming Language :: Python :: 3.11
Classifier: Programming Language :: Python :: 3.12
Classifier: Programming Language :: Python :: 3.13
Requires-Dist: anndata (>=0.11.4)
Requires-Dist: matplotlib (>=3.4)
Requires-Dist: numpy (>=1.20)
Requires-Dist: pandas (>=1.2)
Requires-Dist: scikit-learn (>=1.0)
Requires-Dist: scipy (>=1.6)
Project-URL: Repository, https://github.com/yusuke-imoto-lab/eps-attracting-basin
